discord_grabber/__init__.py
discord_grabber/_resources.py
discord_grabber/exceptions.py
discord_grabber/grabber_class.py
discord_grabber/mail_reader.py
discord_grabber_deskent-1.3.7.dist-info/LICENSE
discord_grabber_deskent-1.3.7.dist-info/METADATA
discord_grabber_deskent-1.3.7.dist-info/WHEEL
discord_grabber_deskent-1.3.7.dist-info/top_level.txt
discord_grabber_deskent-1.3.7.dist-info/RECORD
